karbor/__init__.py
karbor/context.py
karbor/exception.py
karbor/i18n.py
karbor/loadables.py
karbor/manager.py
karbor/policy.py
karbor/quota.py
karbor/resource.py
karbor/rpc.py
karbor/service.py
karbor/utils.py
karbor/version.py
karbor/api/__init__.py
karbor/api/common.py
karbor/api/versions.py
karbor/api/middleware/__init__.py
karbor/api/middleware/auth.py
karbor/api/middleware/fault.py
karbor/api/openstack/__init__.py
karbor/api/openstack/wsgi.py
karbor/api/schemas/__init__.py
karbor/api/schemas/checkpoints.py
karbor/api/schemas/copies.py
karbor/api/schemas/plans.py
karbor/api/schemas/quota_classes.py
karbor/api/schemas/quotas.py
karbor/api/schemas/restores.py
karbor/api/schemas/scheduled_operations.py
karbor/api/schemas/triggers.py
karbor/api/schemas/verifications.py
karbor/api/v1/__init__.py
karbor/api/v1/copies.py
karbor/api/v1/operation_logs.py
karbor/api/v1/plans.py
karbor/api/v1/protectables.py
karbor/api/v1/providers.py
karbor/api/v1/quota_classes.py
karbor/api/v1/quotas.py
karbor/api/v1/restores.py
karbor/api/v1/router.py
karbor/api/v1/scheduled_operations.py
karbor/api/v1/services.py
karbor/api/v1/triggers.py
karbor/api/v1/verifications.py
karbor/api/validation/__init__.py
karbor/api/validation/parameter_types.py
karbor/api/validation/validators.py
karbor/cmd/__init__.py
karbor/cmd/api.py
karbor/cmd/manage.py
karbor/cmd/operationengine.py
karbor/cmd/protection.py
karbor/cmd/status.py
karbor/common/__init__.py
karbor/common/config.py
karbor/common/constants.py
karbor/common/karbor_keystone_plugin.py
karbor/common/notification.py
karbor/common/opts.py
karbor/db/__init__.py
karbor/db/api.py
karbor/db/base.py
karbor/db/migration.py
karbor/db/sqlalchemy/__init__.py
karbor/db/sqlalchemy/api.py
karbor/db/sqlalchemy/models.py
karbor/db/sqlalchemy/migrate_repo/README
karbor/db/sqlalchemy/migrate_repo/__init__.py
karbor/db/sqlalchemy/migrate_repo/manage.py
karbor-1.6.0.dist-info/DESCRIPTION.rst
karbor-1.6.0.dist-info/METADATA
karbor-1.6.0.dist-info/RECORD
karbor-1.6.0.dist-info/WHEEL
karbor-1.6.0.dist-info/entry_points.txt
karbor-1.6.0.dist-info/metadata.json
karbor-1.6.0.dist-info/pbr.json
karbor-1.6.0.dist-info/top_level.txt
