Metadata-Version: 2.0
Name: karbor
Version: 1.6.0
Summary: Application Data Protection as a Service for OpenStack
Home-page: https://docs.openstack.org/karbor/latest/
Author: OpenStack
Author-email: openstack-discuss@lists.openstack.org
License: UNKNOWN
Platform: UNKNOWN
Classifier: Environment :: OpenStack
Classifier: Intended Audience :: Information Technology
Classifier: Intended Audience :: System Administrators
Classifier: License :: OSI Approved :: Apache Software License
Classifier: Operating System :: POSIX :: Linux
Classifier: Programming Language :: Python
Classifier: Programming Language :: Python :: Implementation :: CPython
Classifier: Programming Language :: Python :: 3 :: Only
Classifier: Programming Language :: Python :: 3
Classifier: Programming Language :: Python :: 3.6
Classifier: Programming Language :: Python :: 3.7
Requires-Python: >=3.6
Requires-Dist: Babel (!=2.4.0,>=2.3.4)
Requires-Dist: Paste (>=2.0.2)
Requires-Dist: PasteDeploy (>=1.5.0)
Requires-Dist: Routes (>=2.3.1)
Requires-Dist: SQLAlchemy (!=1.1.5,!=1.1.6,!=1.1.7,!=1.1.8,>=1.0.10)
Requires-Dist: WebOb (>=1.7.1)
Requires-Dist: abclient (>=0.2.3)
Requires-Dist: botocore (>=1.5.1)
Requires-Dist: croniter (>=0.3.4)
Requires-Dist: eventlet (!=0.18.3,!=0.20.1,>=0.18.2)
Requires-Dist: futurist (>=1.8.0)
Requires-Dist: greenlet (>=0.4.10)
Requires-Dist: icalendar (>=3.10)
Requires-Dist: jsonschema (>=2.6.0)
Requires-Dist: keystoneauth1 (>=3.4.0)
Requires-Dist: keystonemiddleware (>=4.18.0)
Requires-Dist: kubernetes (>=5.0.0)
Requires-Dist: oslo.concurrency (>=3.26.0)
Requires-Dist: oslo.config (>=5.2.0)
Requires-Dist: oslo.context (>=2.19.2)
Requires-Dist: oslo.db (>=4.27.0)
Requires-Dist: oslo.i18n (>=3.15.3)
Requires-Dist: oslo.log (>=3.36.0)
Requires-Dist: oslo.messaging (>=5.29.0)
Requires-Dist: oslo.middleware (>=3.31.0)
Requires-Dist: oslo.policy (>=1.30.0)
Requires-Dist: oslo.serialization (!=2.19.1,>=2.18.0)
Requires-Dist: oslo.service (!=1.28.1,>=1.24.0)
Requires-Dist: oslo.upgradecheck (>=0.1.0)
Requires-Dist: oslo.versionedobjects (>=1.31.2)
Requires-Dist: pbr (!=2.1.0,>=2.0.0)
Requires-Dist: python-cinderclient (>=3.3.0)
Requires-Dist: python-freezerclient (>=1.3.0)
Requires-Dist: python-glanceclient (>=2.8.0)
Requires-Dist: python-karborclient (>=0.6.0)
Requires-Dist: python-manilaclient (>=1.16.0)
Requires-Dist: python-neutronclient (>=6.7.0)
Requires-Dist: python-novaclient (>=9.1.0)
Requires-Dist: python-swiftclient (>=3.2.0)
Requires-Dist: python-troveclient (>=2.2.0)
Requires-Dist: requests (>=2.14.2)
Requires-Dist: six (>=1.10.0)
Requires-Dist: sqlalchemy-migrate (>=0.11.0)
Requires-Dist: stevedore (>=1.20.0)
Requires-Dist: taskflow (>=2.16.0)
